xthttp/__init__.py
xthttp/ahttp.py
xthttp/http.py
xthttp/headers/__init__.py
xthttp/headers/defaults.py
xthttp/headers/timeout.py
xthttp/headers/user_agent.py
xthttp/resp/__init__.py
xthttp/resp/adapters.py
xthttp/resp/dom_parser.py
xthttp/resp/encoding.py
xthttp/resp/unified_resp.py
xthttp-0.1.1.dist-info/licenses/LICENSE
xthttp-0.1.1.dist-info/METADATA
xthttp-0.1.1.dist-info/WHEEL
xthttp-0.1.1.dist-info/top_level.txt
xthttp-0.1.1.dist-info/RECORD
