Metadata-Version: 2.4
Name: xthttp
Version: 0.1.1
Summary: A high-performance Python HTTP client library with sync/async support, intelligent encoding detection, and DOM parsing capabilities
Author-email: sandorn <sandorn@live.cn>
License: MIT License
Project-URL: homepage, https://github.com/sandorn/xthttp
Project-URL: repository, https://github.com/sandorn/xthttp
Project-URL: documentation, https://github.com/sandorn/xthttp/wiki
Keywords: http,client,async,requests,aiohttp,scraping,encoding,dom
Classifier: Development Status :: 4 - Beta
Classifier: Intended Audience :: Developers
Classifier: License :: OSI Approved :: MIT License
Classifier: Programming Language :: Python :: 3.13
Classifier: Topic :: Software Development :: Libraries :: Python Modules
Classifier: Topic :: Internet :: WWW/HTTP :: HTTP Servers
Classifier: Topic :: Internet :: WWW/HTTP :: Browsers
Classifier: Topic :: Text Processing :: Markup :: HTML
Classifier: Topic :: Utilities
Classifier: Operating System :: OS Independent
Requires-Python: >=3.13
License-File: LICENSE
Requires-Dist: requests>=2.31.0
Requires-Dist: aiohttp>=3.8.0
Requires-Dist: lxml>=4.9.0
Requires-Dist: pyquery>=2.0.0
Requires-Dist: chardet>=5.0.0
Requires-Dist: fake-useragent>=1.4.0
Requires-Dist: xtwraps>=0.1.0
Requires-Dist: xtlog>=0.1.7
Requires-Dist: yarl>=1.22.0
Requires-Dist: html5lib>=1.1
Provides-Extra: test
Requires-Dist: pytest>=7.3.0; extra == "test"
Requires-Dist: pytest-asyncio>=0.21.0; extra == "test"
Requires-Dist: pytest-cov>=4.1.0; extra == "test"
Dynamic: license-file
